odoo/addons/website_sale_hide_price/README.rst
odoo/addons/website_sale_hide_price/__init__.py
odoo/addons/website_sale_hide_price/__manifest__.py
odoo/addons/website_sale_hide_price/i18n/ar.po
odoo/addons/website_sale_hide_price/i18n/bg.po
odoo/addons/website_sale_hide_price/i18n/bs.po
odoo/addons/website_sale_hide_price/i18n/ca.po
odoo/addons/website_sale_hide_price/i18n/cs.po
odoo/addons/website_sale_hide_price/i18n/da.po
odoo/addons/website_sale_hide_price/i18n/de.po
odoo/addons/website_sale_hide_price/i18n/el_GR.po
odoo/addons/website_sale_hide_price/i18n/en_GB.po
odoo/addons/website_sale_hide_price/i18n/es.po
odoo/addons/website_sale_hide_price/i18n/es_AR.po
odoo/addons/website_sale_hide_price/i18n/es_CL.po
odoo/addons/website_sale_hide_price/i18n/es_CO.po
odoo/addons/website_sale_hide_price/i18n/es_CR.po
odoo/addons/website_sale_hide_price/i18n/es_DO.po
odoo/addons/website_sale_hide_price/i18n/es_EC.po
odoo/addons/website_sale_hide_price/i18n/es_MX.po
odoo/addons/website_sale_hide_price/i18n/es_PE.po
odoo/addons/website_sale_hide_price/i18n/et.po
odoo/addons/website_sale_hide_price/i18n/eu.po
odoo/addons/website_sale_hide_price/i18n/fa.po
odoo/addons/website_sale_hide_price/i18n/fi.po
odoo/addons/website_sale_hide_price/i18n/fr.po
odoo/addons/website_sale_hide_price/i18n/gl.po
odoo/addons/website_sale_hide_price/i18n/he.po
odoo/addons/website_sale_hide_price/i18n/hr.po
odoo/addons/website_sale_hide_price/i18n/hr_HR.po
odoo/addons/website_sale_hide_price/i18n/hu.po
odoo/addons/website_sale_hide_price/i18n/id.po
odoo/addons/website_sale_hide_price/i18n/it.po
odoo/addons/website_sale_hide_price/i18n/ja.po
odoo/addons/website_sale_hide_price/i18n/ko.po
odoo/addons/website_sale_hide_price/i18n/lt.po
odoo/addons/website_sale_hide_price/i18n/lv.po
odoo/addons/website_sale_hide_price/i18n/mk.po
odoo/addons/website_sale_hide_price/i18n/mn.po
odoo/addons/website_sale_hide_price/i18n/nb.po
odoo/addons/website_sale_hide_price/i18n/nl.po
odoo_addon_website_sale_hide_price-18.0.1.0.0.5.dist-info/METADATA
odoo_addon_website_sale_hide_price-18.0.1.0.0.5.dist-info/WHEEL
odoo_addon_website_sale_hide_price-18.0.1.0.0.5.dist-info/top_level.txt
odoo_addon_website_sale_hide_price-18.0.1.0.0.5.dist-info/RECORD
